{
  "name": "Remove corruption",
  "type": "spell",
  "img": "icons/magic/unholy/hand-claw-fire-blue.webp",
  "system": {
    "description": "Removes 20 Corruption from the body at the cost of 2d4 Health. This Health cannot be restored by magic or miracles.",
    "options": [
      "divine",
      "magic"
    ],
    "spellRanks": [
      "wild",
      "apprentice",
      "expert",
      "master",
      "grandmaster"
    ],
    "miracleRanks": [
      "novice",
      "acolyte",
      "cleric"
    ],
    "effectOptions": [
      "and",
      "or"
    ],
    "effectTypes": [],
    "classOptions": [
      "support",
      "lesser",
      "greater"
    ],
    "spellTypes": [
      "fire",
      "water",
      "air",
      "earth",
      "spirit",
      "body",
      "darkness",
      "blood",
      "gnosis"
    ],
    "dmgTypes": [
      "fire",
      "frost",
      "lightning",
      "acid",
      "poison",
      "magic",
      "dark",
      "physical",
      "psychic",
      "blunt",
      "piercing",
      "slash"
    ],
    "testOptions": [
      "Strength",
      "Dexterity",
      "Endurance",
      "Inteligence",
      "Will",
      "Charisma",
      "Perception"
    ],
    "resources": [
      {
        "mode": "",
        "amount": "",
        "type": ""
      }
    ],
    "resourceOptions": {
      "modes": [
        "add",
        "burn"
      ],
      "types": [
        ""
      ]
    },
    "isOffensive": false,
    "difficulty": 25,
    "cost": 4,
    "perRound": 0,
    "option": "magic",
    "type": "darkness",
    "rank": "apprentice",
    "actionCost": "1",
    "range": "caster",
    "spellClass": "support",
    "roll": {
      "diceNum": 2,
      "diceSize": "4",
      "diceBonus": ""
    },
    "penetration": 0,
    "dmgType1": "",
    "bool2": "",
    "dmgType2": "",
    "bool3": "",
    "dmgType3": "",
    "bool4": "",
    "dmgType4": "",
    "effects": {
      "effect1": "0",
      "effect2": "0",
      "effect3": "0",
      "effect4": "0",
      "stun": null,
      "bleed": null,
      "extra1": null,
      "extra2": null,
      "extra3": null
    },
    "effectType1": "",
    "effectType2": "",
    "effectType3": ""
  },
  "effects": [],
  "folder": "dNkZeCgBcF5AHOTZ",
  "flags": {
    "scene-packer": {
      "hash": "8b54e4dbcd41f2280f141b4d1ef4af44753e4e32"
    }
  },
  "_stats": {
    "compendiumSource": "Compendium.world.dark-spells.Item.J1iZ8JSkWtznyfwb",
    "duplicateSource": null,
    "exportSource": null,
    "coreVersion": "13.351",
    "systemId": "tos",
    "systemVersion": "0.6.4c",
    "createdTime": 1770135131840,
    "modifiedTime": 1770135131840,
    "lastModifiedBy": "J03KIFAyMdNdBOUD"
  },
  "ownership": {
    "default": 0,
    "J03KIFAyMdNdBOUD": 3
  },
  "_id": "ucctSgHWhJVY9aYH",
  "sort": 0,
  "_key": "!items!ucctSgHWhJVY9aYH"
}
